threema_work_api_client-1.7.3.dist-info/METADATA
threema_work_api_client-1.7.3.dist-info/WHEEL
threema_work_api_client-1.7.3.dist-info/entry_points.txt
threema_work_api_client/__init__.py
threema_work_api_client/api/__init__.py
threema_work_api_client/api/app_configuration/__init__.py
threema_work_api_client/api/app_configuration/create_global_app_configuration.py
threema_work_api_client/api/app_configuration/create_individual_app_configuration.py
threema_work_api_client/api/app_configuration/delete_global_app_configuration.py
threema_work_api_client/api/app_configuration/delete_individual_app_configuration.py
threema_work_api_client/api/app_configuration/get_bulk_individual_app_configurations.py
threema_work_api_client/api/app_configuration/get_global_app_configuration.py
threema_work_api_client/api/app_configuration/get_global_app_configurations.py
threema_work_api_client/api/app_configuration/get_individual_app_configuration.py
threema_work_api_client/api/app_configuration/get_individual_app_configurations.py
threema_work_api_client/api/app_configuration/update_bulk_individual_app_configurations.py
threema_work_api_client/api/app_configuration/update_global_app_configuration.py
threema_work_api_client/api/app_configuration/update_individual_app_configuration.py
threema_work_api_client/api/contacts/__init__.py
threema_work_api_client/api/contacts/create_contact.py
threema_work_api_client/api/contacts/delete_contact.py
threema_work_api_client/api/contacts/get_category.py
threema_work_api_client/api/contacts/get_contact.py
threema_work_api_client/api/contacts/get_contact_categories.py
threema_work_api_client/api/contacts/get_contacts.py
threema_work_api_client/api/contacts/update_contact.py
threema_work_api_client/api/credentials/__init__.py
threema_work_api_client/api/credentials/create_credential.py
threema_work_api_client/api/credentials/delete_credential.py
threema_work_api_client/api/credentials/get_credential.py
threema_work_api_client/api/credentials/get_credentials.py
threema_work_api_client/api/credentials/update_credential.py
threema_work_api_client/api/logos/__init__.py
threema_work_api_client-1.7.3.dist-info/RECORD
