Metadata-Version: 2.1
Name: threema-work-api-client
Version: 1.7.3
Summary: A client library for accessing Threema Work API
Author-Email: Stanislav <ih3xcode@protonmail.com>
Requires-Python: <4.0,>=3.9
Requires-Dist: httpx<0.29.0,>=0.20.0
Requires-Dist: attrs>=22.2.0
Requires-Dist: python-dateutil>=2.8.0
